logop/__init__.py
logop/_ease.py
logop/_state.py
logop/base.py
logop/constants.py
logop/decorators.py
logop/exceptions.py
logop/logging.py
logop/stream.py
logop/typeins.py
logop/utils.py
logop-1.3.5.dist-info/LICENSE
logop-1.3.5.dist-info/METADATA
logop-1.3.5.dist-info/WHEEL
logop-1.3.5.dist-info/top_level.txt
logop-1.3.5.dist-info/RECORD
