Metadata-Version: 2.1
Name: logop
Version: 1.3.5
Summary: This is a lightweight and scalable Python logging library.
Home-page: https://github.com/numlinka/pylogop
Author: numlinka
Author-email: numlinka@163.com
License: MIT
Keywords: sample,extensible,logging
Platform: UNKNOWN
Classifier: License :: OSI Approved :: MIT License
Classifier: Programming Language :: Python :: 3
Requires-Dist: typex>=0.3.0
